lektor_google_search.py
lektor_google_search-0.1.dist-info/LICENSE
lektor_google_search-0.1.dist-info/METADATA
lektor_google_search-0.1.dist-info/WHEEL
lektor_google_search-0.1.dist-info/entry_points.txt
lektor_google_search-0.1.dist-info/top_level.txt
lektor_google_search-0.1.dist-info/RECORD
