Metadata-Version: 2.1
Name: lektor-google-search
Version: 0.1
Summary: Lektor plugin to add google seach to a website
Home-page: https://github.com/eldjoko/lektor-google-search
Author: Lissan Zahid
Author-email: lissane2013@gmail.com
License: MIT
Keywords: Lektor plugin
Platform: UNKNOWN
Classifier: Framework :: Lektor
Classifier: Environment :: Web Environment
Classifier: Environment :: Plugins
Classifier: License :: OSI Approved :: MIT License
